README.txt
setup.cfg
setup.py
Products/__init__.py
Products.TimeRangeWidget.egg-info/PKG-INFO
Products.TimeRangeWidget.egg-info/SOURCES.txt
Products.TimeRangeWidget.egg-info/dependency_links.txt
Products.TimeRangeWidget.egg-info/entry_points.txt
Products.TimeRangeWidget.egg-info/namespace_packages.txt
Products.TimeRangeWidget.egg-info/not-zip-safe
Products.TimeRangeWidget.egg-info/requires.txt
Products.TimeRangeWidget.egg-info/top_level.txt
Products/TimeRangeWidget/__init__.py
Products/TimeRangeWidget/config.py
Products/TimeRangeWidget/configure.zcml
Products/TimeRangeWidget/utils.py
Products/TimeRangeWidget/validator.py
Products/TimeRangeWidget/widget.py
Products/TimeRangeWidget/i18n/TimeRangeWidget-de-plone.po
Products/TimeRangeWidget/i18n/TimeRangeWidget-fr-plone.po
Products/TimeRangeWidget/profiles/default/metadata.xml
Products/TimeRangeWidget/profiles/default/skins.xml
Products/TimeRangeWidget/skins/timerange_widget/timerange_widget.pt
docs/HISTORY.txt