Metadata-Version: 1.0
Name: Products.TimeRangeWidget
Version: 2.0b3
Summary: Archetypes widget to store a time range
Home-page: http://raptus.com
Author: Raptus AG
Author-email: dev@raptus.com
License: GPL
Platform: UNKNOWN
Classifier: Programming Language :: Python
Classifier: Topic :: Software Development :: Libraries :: Python Modules
